{
  "info": {
    "name": "School Management System API",
    "_postman_id": "9f8e7d6c-5b4a-4321-90ab-cdef12345678",
    "description": "Postman collection for testing the School Management System API endpoints.",
    "version": "1.0.0",
    "schema": "https://schema.getpostman.com/json/collection/v2.1.0/collection.json"
  },
  "variable": [
    {
      "key": "baseUrl",
      "value": "http://localhost:5001"
    },
    {
      "key": "token",
      "value": ""
    },
    {
      "key": "id",
      "value": ""
    },
    {
      "key": "student_id",
      "value": ""
    }
  ],
  "item": [
    {
      "name": "Authentication",
      "item": [
        {
          "name": "Register User",
          "request": {
            "method": "POST",
            "header": [
              {
                "key": "Content-Type",
                "value": "application/json"
              }
            ],
            "body": {
              "mode": "raw",
              "raw": "{\"email\":\"string\",\"password\":\"string\",\"role\":\"string\"}"
            },
            "url": {
              "raw": "{{baseUrl}}/api/auth/register",
              "host": [
                "{{baseUrl}}"
              ],
              "path": [
                "api",
                "auth",
                "register"
              ]
            }
          },
          "response": []
        },
        {
          "name": "Login User",
          "request": {
            "method": "POST",
            "header": [
              {
                "key": "Content-Type",
                "value": "application/json"
              }
            ],
            "body": {
              "mode": "raw",
              "raw": "{\"email\":\"string\",\"password\":\"string\"}"
            },
            "url": {
              "raw": "{{baseUrl}}/api/auth/login",
              "host": [
                "{{baseUrl}}"
              ],
              "path": [
                "api",
                "auth",
                "login"
              ]
            }
          },
          "response": []
        },
        {
          "name": "Get Current User",
          "request": {
            "method": "GET",
            "header": [
              {
                "key": "Authorization",
                "value": "Bearer {{token}}"
              }
            ],
            "url": {
              "raw": "{{baseUrl}}/api/auth/me",
              "host": [
                "{{baseUrl}}"
              ],
              "path": [
                "api",
                "auth",
                "me"
              ]
            }
          },
          "response": []
        }
      ]
    },
    {
      "name": "Students",
      "item": [
        {
          "name": "List All Students",
          "request": {
            "method": "GET",
            "header": [
              {
                "key": "Authorization",
                "value": "Bearer {{token}}"
              }
            ],
            "url": {
              "raw": "{{baseUrl}}/api/students",
              "host": [
                "{{baseUrl}}"
              ],
              "path": [
                "api",
                "students"
              ]
            }
          },
          "response": []
        },
        {
          "name": "Get Student by ID",
          "request": {
            "method": "GET",
            "header": [
              {
                "key": "Authorization",
                "value": "Bearer {{token}}"
              }
            ],
            "url": {
              "raw": "{{baseUrl}}/api/students/{{id}}",
              "host": [
                "{{baseUrl}}"
              ],
              "path": [
                "api",
                "students",
                "{{id}}"
              ]
            }
          },
          "response": []
        },
        {
          "name": "Create Student",
          "request": {
            "method": "POST",
            "header": [
              {
                "key": "Content-Type",
                "value": "application/json"
              }
            ],
            "body": {
              "mode": "raw",
              "raw": "{\"name\":\"string\",\"classId\":\"string\",\"email\":\"string\"}"
            },
            "url": {
              "raw": "{{baseUrl}}/api/students",
              "host": [
                "{{baseUrl}}"
              ],
              "path": [
                "api",
                "students"
              ]
            }
          },
          "response": []
        },
        {
          "name": "Update Student",
          "request": {
            "method": "PUT",
            "header": [
              {
                "key": "Content-Type",
                "value": "application/json"
              }
            ],
            "body": {
              "mode": "raw",
              "raw": "{\"name\":\"string\",\"classId\":\"string\",\"email\":\"string\"}"
            },
            "url": {
              "raw": "{{baseUrl}}/api/students/{{id}}",
              "host": [
                "{{baseUrl}}"
              ],
              "path": [
                "api",
                "students",
                "{{id}}"
              ]
            }
          },
          "response": []
        },
        {
          "name": "Delete Student",
          "request": {
            "method": "DELETE",
            "header": [],
            "url": {
              "raw": "{{baseUrl}}/api/students/{{id}}",
              "host": [
                "{{baseUrl}}"
              ],
              "path": [
                "api",
                "students",
                "{{id}}"
              ]
            }
          },
          "response": []
        }
      ]
    },
    {
      "name": "Teachers",
      "item": [
        {
          "name": "List All Teachers",
          "request": {
            "method": "GET",
            "header": [
              {
                "key": "Authorization",
                "value": "Bearer {{token}}"
              }
            ],
            "url": {
              "raw": "{{baseUrl}}/api/teachers",
              "host": [
                "{{baseUrl}}"
              ],
              "path": [
                "api",
                "teachers"
              ]
            }
          },
          "response": []
        },
        {
          "name": "Get Teacher by ID",
          "request": {
            "method": "GET",
            "header": [
              {
                "key": "Authorization",
                "value": "Bearer {{token}}"
              }
            ],
            "url": {
              "raw": "{{baseUrl}}/api/teachers/{{id}}",
              "host": [
                "{{baseUrl}}"
              ],
              "path": [
                "api",
                "teachers",
                "{{id}}"
              ]
            }
          },
          "response": []
        },
        {
          "name": "Create Teacher",
          "request": {
            "method": "POST",
            "header": [
              {
                "key": "Content-Type",
                "value": "application/json"
              }
            ],
            "body": {
              "mode": "raw",
              "raw": "{\"name\":\"string\",\"email\":\"string\"}"
            },
            "url": {
              "raw": "{{baseUrl}}/api/teachers",
              "host": [
                "{{baseUrl}}"
              ],
              "path": [
                "api",
                "teachers"
              ]
            }
          },
          "response": []
        },
        {
          "name": "Update Teacher",
          "request": {
            "method": "PUT",
            "header": [
              {
                "key": "Content-Type",
                "value": "application/json"
              }
            ],
            "body": {
              "mode": "raw",
              "raw": "{\"name\":\"string\",\"email\":\"string\"}"
            },
            "url": {
              "raw": "{{baseUrl}}/api/teachers/{{id}}",
              "host": [
                "{{baseUrl}}"
              ],
              "path": [
                "api",
                "teachers",
                "{{id}}"
              ]
            }
          },
          "response": []
        }
      ]
    },
    {
      "name": "Classes",
      "item": [
        {
          "name": "List All Classes",
          "request": {
            "method": "GET",
            "header": [
              {
                "key": "Authorization",
                "value": "Bearer {{token}}"
              }
            ],
            "url": {
              "raw": "{{baseUrl}}/api/classes",
              "host": [
                "{{baseUrl}}"
              ],
              "path": [
                "api",
                "classes"
              ]
            }
          },
          "response": []
        },
        {
          "name": "Get Class by ID",
          "request": {
            "method": "GET",
            "header": [
              {
                "key": "Authorization",
                "value": "Bearer {{token}}"
              }
            ],
            "url": {
              "raw": "{{baseUrl}}/api/classes/{{id}}",
              "host": [
                "{{baseUrl}}"
              ],
              "path": [
                "api",
                "classes",
                "{{id}}"
              ]
            }
          },
          "response": []
        },
        {
          "name": "Create Class",
          "request": {
            "method": "POST",
            "header": [
              {
                "key": "Content-Type",
                "value": "application/json"
              }
            ],
            "body": {
              "mode": "raw",
              "raw": "{\"name\":\"string\"}"
            },
            "url": {
              "raw": "{{baseUrl}}/api/classes",
              "host": [
                "{{baseUrl}}"
              ],
              "path": [
                "api",
                "classes"
              ]
            }
          },
          "response": []
        },
        {
          "name": "Update Class",
          "request": {
            "method": "PUT",
            "header": [
              {
                "key": "Content-Type",
                "value": "application/json"
              }
            ],
            "body": {
              "mode": "raw",
              "raw": "{\"name\":\"string\"}"
            },
            "url": {
              "raw": "{{baseUrl}}/api/classes/{{id}}",
              "host": [
                "{{baseUrl}}"
              ],
              "path": [
                "api",
                "classes",
                "{{id}}"
              ]
            }
          },
          "response": []
        }
      ]
    },
    {
      "name": "Subjects",
      "item": [
        {
          "name": "List All Subjects",
          "request": {
            "method": "GET",
            "header": [
              {
                "key": "Authorization",
                "value": "Bearer {{token}}"
              }
            ],
            "url": {
              "raw": "{{baseUrl}}/api/subjects",
              "host": [
                "{{baseUrl}}"
              ],
              "path": [
                "api",
                "subjects"
              ]
            }
          },
          "response": []
        },
        {
          "name": "Get Subject by ID",
          "request": {
            "method": "GET",
            "header": [
              {
                "key": "Authorization",
                "value": "Bearer {{token}}"
              }
            ],
            "url": {
              "raw": "{{baseUrl}}/api/subjects/{{id}}",
              "host": [
                "{{baseUrl}}"
              ],
              "path": [
                "api",
                "subjects",
                "{{id}}"
              ]
            }
          },
          "response": []
        },
        {
          "name": "Create Subject",
          "request": {
            "method": "POST",
            "header": [
              {
                "key": "Content-Type",
                "value": "application/json"
              }
            ],
            "body": {
              "mode": "raw",
              "raw": "{\"name\":\"string\"}"
            },
            "url": {
              "raw": "{{baseUrl}}/api/subjects",
              "host": [
                "{{baseUrl}}"
              ],
              "path": [
                "api",
                "subjects"
              ]
            }
          },
          "response": []
        }
      ]
    },
    {
      "name": "Fees",
      "item": [
        {
          "name": "List All Fees",
          "request": {
            "method": "GET",
            "header": [
              {
                "key": "Authorization",
                "value": "Bearer {{token}}"
              }
            ],
            "url": {
              "raw": "{{baseUrl}}/api/fees",
              "host": [
                "{{baseUrl}}"
              ],
              "path": [
                "api",
                "fees"
              ]
            }
          },
          "response": []
        },
        {
          "name": "Get Student Fees",
          "request": {
            "method": "GET",
            "header": [
              {
                "key": "Authorization",
                "value": "Bearer {{token}}"
              }
            ],
            "url": {
              "raw": "{{baseUrl}}/api/fees/student/{{student_id}}",
              "host": [
                "{{baseUrl}}"
              ],
              "path": [
                "api",
                "fees",
                "student",
                "{{student_id}}"
              ]
            }
          },
          "response": []
        },
        {
          "name": "Create Fee",
          "request": {
            "method": "POST",
            "header": [
              {
                "key": "Content-Type",
                "value": "application/json"
              }
            ],
            "body": {
              "mode": "raw",
              "raw": "{\"studentId\":\"string\",\"amount\":\"number\"}"
            },
            "url": {
              "raw": "{{baseUrl}}/api/fees",
              "host": [
                "{{baseUrl}}"
              ],
              "path": [
                "api",
                "fees"
              ]
            }
          },
          "response": []
        },
        {
          "name": "Record Payment",
          "request": {
            "method": "POST",
            "header": [
              {
                "key": "Content-Type",
                "value": "application/json"
              }
            ],
            "body": {
              "mode": "raw",
              "raw": "{\"feeId\":\"string\",\"amount\":\"number\"}"
            },
            "url": {
              "raw": "{{baseUrl}}/api/fees/payment",
              "host": [
                "{{baseUrl}}"
              ],
              "path": [
                "api",
                "fees",
                "payment"
              ]
            }
          },
          "response": []
        }
      ]
    },
    {
      "name": "Absences",
      "item": [
        {
          "name": "List All Absences",
          "request": {
            "method": "GET",
            "header": [
              {
                "key": "Authorization",
                "value": "Bearer {{token}}"
              }
            ],
            "url": {
              "raw": "{{baseUrl}}/api/absences",
              "host": [
                "{{baseUrl}}"
              ],
              "path": [
                "api",
                "absences"
              ]
            }
          },
          "response": []
        },
        {
          "name": "Record Absence",
          "request": {
            "method": "POST",
            "header": [
              {
                "key": "Content-Type",
                "value": "application/json"
              }
            ],
            "body": {
              "mode": "raw",
              "raw": "{\"studentId\":\"string\",\"date\":\"string\"}"
            },
            "url": {
              "raw": "{{baseUrl}}/api/absences",
              "host": [
                "{{baseUrl}}"
              ],
              "path": [
                "api",
                "absences"
              ]
            }
          },
          "response": []
        },
        {
          "name": "Update Absence",
          "request": {
            "method": "PUT",
            "header": [
              {
                "key": "Content-Type",
                "value": "application/json"
              }
            ],
            "body": {
              "mode": "raw",
              "raw": "{\"approved\":true}"
            },
            "url": {
              "raw": "{{baseUrl}}/api/absences/{{id}}",
              "host": [
                "{{baseUrl}}"
              ],
              "path": [
                "api",
                "absences",
                "{{id}}"
              ]
            }
          },
          "response": []
        }
      ]
    }
  ]
}